[
    {
        "model": "admin.logentry",
        "pk": 1,
        "fields": {
            "action_time": "2025-09-12T14:35:19.503Z",
            "user": 1,
            "content_type": 7,
            "object_id": "1",
            "object_repr": "Collect object (1)",
            "action_flag": 1,
            "change_message": "[{\"added\": {}}]"
        }
    },
    {
        "model": "admin.logentry",
        "pk": 2,
        "fields": {
            "action_time": "2025-09-12T14:35:46.422Z",
            "user": 1,
            "content_type": 7,
            "object_id": "2",
            "object_repr": "Collect object (2)",
            "action_flag": 1,
            "change_message": "[{\"added\": {}}]"
        }
    },
    {
        "model": "admin.logentry",
        "pk": 3,
        "fields": {
            "action_time": "2025-09-12T14:36:10.712Z",
            "user": 1,
            "content_type": 7,
            "object_id": "3",
            "object_repr": "Collect object (3)",
            "action_flag": 1,
            "change_message": "[{\"added\": {}}]"
        }
    },
    {
        "model": "admin.logentry",
        "pk": 4,
        "fields": {
            "action_time": "2025-09-12T14:36:50.277Z",
            "user": 1,
            "content_type": 7,
            "object_id": "4",
            "object_repr": "Collect object (4)",
            "action_flag": 1,
            "change_message": "[{\"added\": {}}]"
        }
    },
    {
        "model": "admin.logentry",
        "pk": 5,
        "fields": {
            "action_time": "2025-09-12T14:37:14.595Z",
            "user": 1,
            "content_type": 7,
            "object_id": "2",
            "object_repr": "Collect object (2)",
            "action_flag": 2,
            "change_message": "[{\"changed\": {\"fields\": [\"\\u041d\\u0430\\u0437\\u0432\\u0430\\u043d\\u0438\\u0435 \\u0441\\u0431\\u043e\\u0440\\u0430\"]}}]"
        }
    },
    {
        "model": "admin.logentry",
        "pk": 6,
        "fields": {
            "action_time": "2025-09-12T14:38:07.861Z",
            "user": 1,
            "content_type": 7,
            "object_id": "5",
            "object_repr": "Collect object (5)",
            "action_flag": 1,
            "change_message": "[{\"added\": {}}]"
        }
    },
    {
        "model": "admin.logentry",
        "pk": 7,
        "fields": {
            "action_time": "2025-09-12T14:46:57.163Z",
            "user": 1,
            "content_type": 8,
            "object_id": "1",
            "object_repr": "Payment object (1)",
            "action_flag": 1,
            "change_message": "[{\"added\": {}}]"
        }
    },
    {
        "model": "admin.logentry",
        "pk": 8,
        "fields": {
            "action_time": "2025-09-12T14:47:15.579Z",
            "user": 1,
            "content_type": 8,
            "object_id": "2",
            "object_repr": "Payment object (2)",
            "action_flag": 1,
            "change_message": "[{\"added\": {}}]"
        }
    },
    {
        "model": "admin.logentry",
        "pk": 9,
        "fields": {
            "action_time": "2025-09-12T14:47:40.577Z",
            "user": 1,
            "content_type": 8,
            "object_id": "3",
            "object_repr": "Payment object (3)",
            "action_flag": 1,
            "change_message": "[{\"added\": {}}]"
        }
    },
    {
        "model": "admin.logentry",
        "pk": 10,
        "fields": {
            "action_time": "2025-09-12T14:47:58.410Z",
            "user": 1,
            "content_type": 8,
            "object_id": "4",
            "object_repr": "Payment object (4)",
            "action_flag": 1,
            "change_message": "[{\"added\": {}}]"
        }
    },
    {
        "model": "admin.logentry",
        "pk": 11,
        "fields": {
            "action_time": "2025-09-12T14:48:16.477Z",
            "user": 1,
            "content_type": 8,
            "object_id": "5",
            "object_repr": "Payment object (5)",
            "action_flag": 1,
            "change_message": "[{\"added\": {}}]"
        }
    },
    {
        "model": "admin.logentry",
        "pk": 12,
        "fields": {
            "action_time": "2025-09-12T14:48:29.405Z",
            "user": 1,
            "content_type": 8,
            "object_id": "6",
            "object_repr": "Payment object (6)",
            "action_flag": 1,
            "change_message": "[{\"added\": {}}]"
        }
    },
    {
        "model": "admin.logentry",
        "pk": 13,
        "fields": {
            "action_time": "2025-09-12T14:48:42.861Z",
            "user": 1,
            "content_type": 8,
            "object_id": "7",
            "object_repr": "Payment object (7)",
            "action_flag": 1,
            "change_message": "[{\"added\": {}}]"
        }
    },
    {
        "model": "admin.logentry",
        "pk": 14,
        "fields": {
            "action_time": "2025-09-12T14:48:59.104Z",
            "user": 1,
            "content_type": 8,
            "object_id": "8",
            "object_repr": "Payment object (8)",
            "action_flag": 1,
            "change_message": "[{\"added\": {}}]"
        }
    },
    {
        "model": "admin.logentry",
        "pk": 15,
        "fields": {
            "action_time": "2025-09-12T14:49:40.465Z",
            "user": 1,
            "content_type": 8,
            "object_id": "9",
            "object_repr": "Payment object (9)",
            "action_flag": 1,
            "change_message": "[{\"added\": {}}]"
        }
    },
    {
        "model": "admin.logentry",
        "pk": 16,
        "fields": {
            "action_time": "2025-09-12T14:49:53.351Z",
            "user": 1,
            "content_type": 8,
            "object_id": "10",
            "object_repr": "Payment object (10)",
            "action_flag": 1,
            "change_message": "[{\"added\": {}}]"
        }
    },
    {
        "model": "auth.permission",
        "pk": 1,
        "fields": {
            "name": "Can add log entry",
            "content_type": 1,
            "codename": "add_logentry"
        }
    },
    {
        "model": "auth.permission",
        "pk": 2,
        "fields": {
            "name": "Can change log entry",
            "content_type": 1,
            "codename": "change_logentry"
        }
    },
    {
        "model": "auth.permission",
        "pk": 3,
        "fields": {
            "name": "Can delete log entry",
            "content_type": 1,
            "codename": "delete_logentry"
        }
    },
    {
        "model": "auth.permission",
        "pk": 4,
        "fields": {
            "name": "Can view log entry",
            "content_type": 1,
            "codename": "view_logentry"
        }
    },
    {
        "model": "auth.permission",
        "pk": 5,
        "fields": {
            "name": "Can add permission",
            "content_type": 2,
            "codename": "add_permission"
        }
    },
    {
        "model": "auth.permission",
        "pk": 6,
        "fields": {
            "name": "Can change permission",
            "content_type": 2,
            "codename": "change_permission"
        }
    },
    {
        "model": "auth.permission",
        "pk": 7,
        "fields": {
            "name": "Can delete permission",
            "content_type": 2,
            "codename": "delete_permission"
        }
    },
    {
        "model": "auth.permission",
        "pk": 8,
        "fields": {
            "name": "Can view permission",
            "content_type": 2,
            "codename": "view_permission"
        }
    },
    {
        "model": "auth.permission",
        "pk": 9,
        "fields": {
            "name": "Can add group",
            "content_type": 3,
            "codename": "add_group"
        }
    },
    {
        "model": "auth.permission",
        "pk": 10,
        "fields": {
            "name": "Can change group",
            "content_type": 3,
            "codename": "change_group"
        }
    },
    {
        "model": "auth.permission",
        "pk": 11,
        "fields": {
            "name": "Can delete group",
            "content_type": 3,
            "codename": "delete_group"
        }
    },
    {
        "model": "auth.permission",
        "pk": 12,
        "fields": {
            "name": "Can view group",
            "content_type": 3,
            "codename": "view_group"
        }
    },
    {
        "model": "auth.permission",
        "pk": 13,
        "fields": {
            "name": "Can add user",
            "content_type": 4,
            "codename": "add_user"
        }
    },
    {
        "model": "auth.permission",
        "pk": 14,
        "fields": {
            "name": "Can change user",
            "content_type": 4,
            "codename": "change_user"
        }
    },
    {
        "model": "auth.permission",
        "pk": 15,
        "fields": {
            "name": "Can delete user",
            "content_type": 4,
            "codename": "delete_user"
        }
    },
    {
        "model": "auth.permission",
        "pk": 16,
        "fields": {
            "name": "Can view user",
            "content_type": 4,
            "codename": "view_user"
        }
    },
    {
        "model": "auth.permission",
        "pk": 17,
        "fields": {
            "name": "Can add content type",
            "content_type": 5,
            "codename": "add_contenttype"
        }
    },
    {
        "model": "auth.permission",
        "pk": 18,
        "fields": {
            "name": "Can change content type",
            "content_type": 5,
            "codename": "change_contenttype"
        }
    },
    {
        "model": "auth.permission",
        "pk": 19,
        "fields": {
            "name": "Can delete content type",
            "content_type": 5,
            "codename": "delete_contenttype"
        }
    },
    {
        "model": "auth.permission",
        "pk": 20,
        "fields": {
            "name": "Can view content type",
            "content_type": 5,
            "codename": "view_contenttype"
        }
    },
    {
        "model": "auth.permission",
        "pk": 21,
        "fields": {
            "name": "Can add session",
            "content_type": 6,
            "codename": "add_session"
        }
    },
    {
        "model": "auth.permission",
        "pk": 22,
        "fields": {
            "name": "Can change session",
            "content_type": 6,
            "codename": "change_session"
        }
    },
    {
        "model": "auth.permission",
        "pk": 23,
        "fields": {
            "name": "Can delete session",
            "content_type": 6,
            "codename": "delete_session"
        }
    },
    {
        "model": "auth.permission",
        "pk": 24,
        "fields": {
            "name": "Can view session",
            "content_type": 6,
            "codename": "view_session"
        }
    },
    {
        "model": "auth.permission",
        "pk": 25,
        "fields": {
            "name": "Can add collect",
            "content_type": 7,
            "codename": "add_collect"
        }
    },
    {
        "model": "auth.permission",
        "pk": 26,
        "fields": {
            "name": "Can change collect",
            "content_type": 7,
            "codename": "change_collect"
        }
    },
    {
        "model": "auth.permission",
        "pk": 27,
        "fields": {
            "name": "Can delete collect",
            "content_type": 7,
            "codename": "delete_collect"
        }
    },
    {
        "model": "auth.permission",
        "pk": 28,
        "fields": {
            "name": "Can view collect",
            "content_type": 7,
            "codename": "view_collect"
        }
    },
    {
        "model": "auth.permission",
        "pk": 29,
        "fields": {
            "name": "Can add Платеж",
            "content_type": 8,
            "codename": "add_payment"
        }
    },
    {
        "model": "auth.permission",
        "pk": 30,
        "fields": {
            "name": "Can change Платеж",
            "content_type": 8,
            "codename": "change_payment"
        }
    },
    {
        "model": "auth.permission",
        "pk": 31,
        "fields": {
            "name": "Can delete Платеж",
            "content_type": 8,
            "codename": "delete_payment"
        }
    },
    {
        "model": "auth.permission",
        "pk": 32,
        "fields": {
            "name": "Can view Платеж",
            "content_type": 8,
            "codename": "view_payment"
        }
    },
    {
        "model": "auth.user",
        "pk": 1,
        "fields": {
            "password": "pbkdf2_sha256$1000000$7J1x1Cchhk6WCCDNqCVccq$N5CN/g4OvXqQkCxN1IPipn5XI82uJYXK+wt3bQZ2WoA=",
            "last_login": "2025-09-12T14:34:02.346Z",
            "is_superuser": true,
            "username": "admin",
            "first_name": "",
            "last_name": "",
            "email": "admin@admin.admin",
            "is_staff": true,
            "is_active": true,
            "date_joined": "2025-09-12T14:33:09.569Z",
            "groups": [],
            "user_permissions": []
        }
    },
    {
        "model": "auth.user",
        "pk": 2,
        "fields": {
            "password": "",
            "last_login": null,
            "is_superuser": false,
            "username": "user-0",
            "first_name": "",
            "last_name": "",
            "email": "email-0",
            "is_staff": false,
            "is_active": true,
            "date_joined": "2025-09-12T14:33:30.067Z",
            "groups": [],
            "user_permissions": []
        }
    },
    {
        "model": "auth.user",
        "pk": 3,
        "fields": {
            "password": "",
            "last_login": null,
            "is_superuser": false,
            "username": "user-1",
            "first_name": "",
            "last_name": "",
            "email": "email-1",
            "is_staff": false,
            "is_active": true,
            "date_joined": "2025-09-12T14:33:30.067Z",
            "groups": [],
            "user_permissions": []
        }
    },
    {
        "model": "auth.user",
        "pk": 4,
        "fields": {
            "password": "",
            "last_login": null,
            "is_superuser": false,
            "username": "user-2",
            "first_name": "",
            "last_name": "",
            "email": "email-2",
            "is_staff": false,
            "is_active": true,
            "date_joined": "2025-09-12T14:33:30.067Z",
            "groups": [],
            "user_permissions": []
        }
    },
    {
        "model": "auth.user",
        "pk": 5,
        "fields": {
            "password": "",
            "last_login": null,
            "is_superuser": false,
            "username": "user-3",
            "first_name": "",
            "last_name": "",
            "email": "email-3",
            "is_staff": false,
            "is_active": true,
            "date_joined": "2025-09-12T14:33:30.067Z",
            "groups": [],
            "user_permissions": []
        }
    },
    {
        "model": "auth.user",
        "pk": 6,
        "fields": {
            "password": "",
            "last_login": null,
            "is_superuser": false,
            "username": "user-4",
            "first_name": "",
            "last_name": "",
            "email": "email-4",
            "is_staff": false,
            "is_active": true,
            "date_joined": "2025-09-12T14:33:30.067Z",
            "groups": [],
            "user_permissions": []
        }
    },
    {
        "model": "contenttypes.contenttype",
        "pk": 1,
        "fields": {
            "app_label": "admin",
            "model": "logentry"
        }
    },
    {
        "model": "contenttypes.contenttype",
        "pk": 2,
        "fields": {
            "app_label": "auth",
            "model": "permission"
        }
    },
    {
        "model": "contenttypes.contenttype",
        "pk": 3,
        "fields": {
            "app_label": "auth",
            "model": "group"
        }
    },
    {
        "model": "contenttypes.contenttype",
        "pk": 4,
        "fields": {
            "app_label": "auth",
            "model": "user"
        }
    },
    {
        "model": "contenttypes.contenttype",
        "pk": 5,
        "fields": {
            "app_label": "contenttypes",
            "model": "contenttype"
        }
    },
    {
        "model": "contenttypes.contenttype",
        "pk": 6,
        "fields": {
            "app_label": "sessions",
            "model": "session"
        }
    },
    {
        "model": "contenttypes.contenttype",
        "pk": 7,
        "fields": {
            "app_label": "fees",
            "model": "collect"
        }
    },
    {
        "model": "contenttypes.contenttype",
        "pk": 8,
        "fields": {
            "app_label": "fees",
            "model": "payment"
        }
    },
    {
        "model": "sessions.session",
        "pk": "u1oee45tphtpr6aglb66ipo3ea81ajv6",
        "fields": {
            "session_data": ".eJxVjMsOwiAQRf-FtSHAyMule7-BwAxI1UBS2pXx322TLnR7zzn3zUJclxrWkecwEbswyU6_W4r4zG0H9Ijt3jn2tsxT4rvCDzr4rVN-XQ_376DGUbc6WZLF6wwJjLSeRLHRSSAUDtH7ohV6VEbYMyhjsxLFCQPKCU8bB80-X9mCNyU:1ux4qg:Nr4lmIFBnEtiGrDo9jLQD751EptstQYV1brlU5wvAOg",
            "expire_date": "2025-09-26T14:34:02.349Z"
        }
    },
    {
        "model": "fees.payment",
        "pk": 1,
        "fields": {
            "name": "p1",
            "owner": 1,
            "collection": 3,
            "amount": "100.13",
            "created_at": "2025-09-12T14:46:57.159Z",
            "updated_at": "2025-09-12T14:46:57.159Z"
        }
    },
    {
        "model": "fees.payment",
        "pk": 2,
        "fields": {
            "name": "p2",
            "owner": 3,
            "collection": 5,
            "amount": "2112.32",
            "created_at": "2025-09-12T14:47:15.576Z",
            "updated_at": "2025-09-12T14:47:15.576Z"
        }
    },
    {
        "model": "fees.payment",
        "pk": 3,
        "fields": {
            "name": "p3",
            "owner": 6,
            "collection": 1,
            "amount": "432.12",
            "created_at": "2025-09-12T14:47:40.575Z",
            "updated_at": "2025-09-12T14:47:40.575Z"
        }
    },
    {
        "model": "fees.payment",
        "pk": 4,
        "fields": {
            "name": "p4",
            "owner": 4,
            "collection": 1,
            "amount": "0.01",
            "created_at": "2025-09-12T14:47:58.408Z",
            "updated_at": "2025-09-12T14:47:58.408Z"
        }
    },
    {
        "model": "fees.payment",
        "pk": 5,
        "fields": {
            "name": "p2",
            "owner": 1,
            "collection": 1,
            "amount": "0.13",
            "created_at": "2025-09-12T14:48:16.474Z",
            "updated_at": "2025-09-12T14:48:16.474Z"
        }
    },
    {
        "model": "fees.payment",
        "pk": 6,
        "fields": {
            "name": "p6",
            "owner": 4,
            "collection": 4,
            "amount": "0.03",
            "created_at": "2025-09-12T14:48:29.404Z",
            "updated_at": "2025-09-12T14:48:29.404Z"
        }
    },
    {
        "model": "fees.payment",
        "pk": 7,
        "fields": {
            "name": "p7",
            "owner": 5,
            "collection": 5,
            "amount": "0.04",
            "created_at": "2025-09-12T14:48:42.859Z",
            "updated_at": "2025-09-12T14:48:42.859Z"
        }
    },
    {
        "model": "fees.payment",
        "pk": 8,
        "fields": {
            "name": "p8",
            "owner": 3,
            "collection": 5,
            "amount": "0.08",
            "created_at": "2025-09-12T14:48:59.102Z",
            "updated_at": "2025-09-12T14:48:59.102Z"
        }
    },
    {
        "model": "fees.payment",
        "pk": 9,
        "fields": {
            "name": "p9",
            "owner": 3,
            "collection": 3,
            "amount": "321.32",
            "created_at": "2025-09-12T14:49:40.463Z",
            "updated_at": "2025-09-12T14:49:40.463Z"
        }
    },
    {
        "model": "fees.payment",
        "pk": 10,
        "fields": {
            "name": "p10",
            "owner": 3,
            "collection": 1,
            "amount": "543.32",
            "created_at": "2025-09-12T14:49:53.348Z",
            "updated_at": "2025-09-12T14:49:53.348Z"
        }
    },
    {
        "model": "fees.collect",
        "pk": 1,
        "fields": {
            "name": "c1",
            "author": 1,
            "cause": "AR",
            "description": "lala",
            "planned_amount": "1000.70",
            "image": "",
            "closing_to": "2025-10-12T14:34:44Z"
        }
    },
    {
        "model": "fees.collect",
        "pk": 2,
        "fields": {
            "name": "c4",
            "author": 1,
            "cause": "AR",
            "description": "lala",
            "planned_amount": "1000.50",
            "image": "",
            "closing_to": "2025-10-12T14:35:40Z"
        }
    },
    {
        "model": "fees.collect",
        "pk": 3,
        "fields": {
            "name": "c2",
            "author": 3,
            "cause": "BD",
            "description": "lolo",
            "planned_amount": "7000.13",
            "image": "",
            "closing_to": "2025-11-12T14:36:06Z"
        }
    },
    {
        "model": "fees.collect",
        "pk": 4,
        "fields": {
            "name": "c3",
            "author": 6,
            "cause": "AR",
            "description": "lulu",
            "planned_amount": "5555.00",
            "image": "",
            "closing_to": "2026-09-12T14:36:38Z"
        }
    },
    {
        "model": "fees.collect",
        "pk": 5,
        "fields": {
            "name": "c5",
            "author": 1,
            "cause": "PT",
            "description": "iuu",
            "planned_amount": "123123.12",
            "image": "",
            "closing_to": "2025-09-20T14:37:58Z"
        }
    }
]